conexao/__init__.py
conexao/cli.py
conexao/config.py
conexao/docker.py
conexao/ssh.py
conexao/django/__init__.py
conexao/django/configure.py
conexao/django/auto/__init__.py
conexao/mongodb/__init__.py
conexao/mongodb/client.py
conexao/mongodb/auto/__init__.py
conexao-0.0.11.dist-info/LICENSE
conexao-0.0.11.dist-info/METADATA
conexao-0.0.11.dist-info/WHEEL
conexao-0.0.11.dist-info/entry_points.txt
conexao-0.0.11.dist-info/top_level.txt
conexao-0.0.11.dist-info/RECORD
