Metadata-Version: 2.2
Name: conexao
Version: 0.0.11
Summary: A connection helper.
Project-URL: Homepage, https://gitlab.com/evagio/conexao
Classifier: Programming Language :: Python :: 3
Classifier: License :: OSI Approved :: GNU General Public License v3 or later (GPLv3+)
Requires-Python: >=3.7
License-File: LICENSE
